smartjob/__init__.py
smartjob/app/__init__.py
smartjob/app/exception.py
smartjob/app/execution.py
smartjob/app/executor.py
smartjob/app/input.py
smartjob/app/job.py
smartjob/app/retry.py
smartjob/app/storage.py
smartjob/app/timeout.py
smartjob/app/utils.py
smartjob/infra/__init__.py
smartjob/infra/adapters/__init__.py
smartjob/infra/adapters/executor/__init__.py
smartjob/infra/adapters/executor/cloudbatch.py
smartjob/infra/adapters/executor/cloudrun.py
smartjob/infra/adapters/executor/docker.py
smartjob/infra/adapters/executor/vertex.py
smartjob/infra/adapters/storage/__init__.py
smartjob/infra/adapters/storage/docker.py
smartjob/infra/adapters/storage/gcs.py
smartjob/infra/controllers/__init__.py
smartjob/infra/controllers/cli/__init__.py
smartjob/infra/controllers/cli/common.py
smartjob/infra/controllers/cli/main.py
smartjob/infra/controllers/lib.py
smartjob/py.typed
smartjob-0.0.34.dist-info/METADATA
smartjob-0.0.34.dist-info/WHEEL
smartjob-0.0.34.dist-info/entry_points.txt
smartjob-0.0.34.dist-info/licenses/LICENSE
smartjob-0.0.34.dist-info/RECORD
