Metadata-Version: 2.4
Name: smartjob
Version: 0.0.34
Summary: Little async python library for dealing with GCP/Cloud Run Jobs, GCP/Cloud Batch Jobs, GCP/VertexAI CustomJobs and (local) Docker jobs
License-File: LICENSE
Author: Fabien MARTY
Author-email: fab@fabien-marty.dev
Requires-Python: >=3.11,<4.0
Classifier: Programming Language :: Python :: 3
Classifier: Programming Language :: Python :: 3.11
Classifier: Programming Language :: Python :: 3.12
Classifier: Programming Language :: Python :: 3.13
Classifier: Programming Language :: Python :: 3.14
Requires-Dist: docker (>=7.1.0,<8.0.0)
Requires-Dist: google-cloud-aiplatform (>=1.60.0)
Requires-Dist: google-cloud-batch (>=0.17.35,<0.18.0)
Requires-Dist: google-cloud-compute (>=1.28.0,<2.0.0)
Requires-Dist: google-cloud-run (>=0.10.8)
Requires-Dist: rich (>=13.7.1)
Requires-Dist: setuptools (>=72.1.0)
Requires-Dist: stlog (>=0.2.1)
Requires-Dist: tenacity (>=9.0.0,<10.0.0)
Requires-Dist: typer (>=0.12.3)
